edge_containers_cli/__init__.py
edge_containers_cli/__main__.py
edge_containers_cli/_version.py
edge_containers_cli/autocomplete.py
edge_containers_cli/backend.py
edge_containers_cli/cli.py
edge_containers_cli/definitions.py
edge_containers_cli/git.py
edge_containers_cli/globals.py
edge_containers_cli/logging.py
edge_containers_cli/shell.py
edge_containers_cli/utils.py
edge_containers_cli/cmds/__init__.py
edge_containers_cli/cmds/argo_commands.py
edge_containers_cli/cmds/commands.py
edge_containers_cli/cmds/demo_commands.py
edge_containers_cli/cmds/helm.py
edge_containers_cli/cmds/k8s_commands.py
edge_containers_cli/cmds/monitor.py
edge_containers_cli/cmds/monitor.tcss
edge_containers_cli-4.4.5.dist-info/licenses/LICENSE
edge_containers_cli-4.4.5.dist-info/METADATA
edge_containers_cli-4.4.5.dist-info/WHEEL
edge_containers_cli-4.4.5.dist-info/entry_points.txt
edge_containers_cli-4.4.5.dist-info/top_level.txt
edge_containers_cli-4.4.5.dist-info/RECORD
