Metadata-Version: 2.4
Name: edge-containers-cli
Version: 4.4.5
Summary: CLI for deploying and managing epics containers IOCs and services
Author-email: Giles Knap <giles.knap@gmail.com>
License:                                  Apache License
Project-URL: GitHub, https://github.com/epics-containers/edge-containers-cli
Classifier: Development Status :: 3 - Alpha
Classifier: License :: OSI Approved :: Apache Software License
Classifier: Programming Language :: Python :: 3.10
Classifier: Programming Language :: Python :: 3.11
Classifier: Programming Language :: Python :: 3.12
Requires-Python: >=3.10
License-File: LICENSE
Requires-Dist: natsort
Requires-Dist: typer[all]
Requires-Dist: requests
Requires-Dist: ruamel.yaml
Requires-Dist: jinja2
Requires-Dist: polars-lts-cpu
Requires-Dist: textual
Requires-Dist: urllib3<2.4.0
Provides-Extra: dev
Requires-Dist: copier; extra == "dev"
Requires-Dist: pipdeptree; extra == "dev"
Requires-Dist: pre-commit; extra == "dev"
Requires-Dist: pyright; extra == "dev"
Requires-Dist: pytest; extra == "dev"
Requires-Dist: pytest-cov; extra == "dev"
Requires-Dist: pytest-mock; extra == "dev"
Requires-Dist: ruff; extra == "dev"
Requires-Dist: tox-direct; extra == "dev"
Requires-Dist: types-mock; extra == "dev"
Dynamic: license-file
